slepa/__init__.py
slepa/self_learning_entropic_population_annealing.py
slepa-1.0.0a3.dist-info/LICENSE
slepa-1.0.0a3.dist-info/METADATA
slepa-1.0.0a3.dist-info/WHEEL
slepa-1.0.0a3.dist-info/top_level.txt
slepa-1.0.0a3.dist-info/RECORD
