Metadata-Version: 2.1
Name: slepa
Version: 1.0.0a3
Summary: an interpretable materials design tool based on self-learning entropic population annealing
Home-page: https://github.com/tsudalab/EntropicPopulationAnnealing
Author: SLEPA developers
Author-email: author@example.com
License: GPLv3
Platform: UNKNOWN
Requires-Python: >=3.6
License-File: LICENSE
Requires-Dist: numpy
Requires-Dist: scipy
Requires-Dist: physbo
Requires-Dist: modlamp
